DSP LAB/Exp2_FixedPoint_Operations/exp_2.v
module exp_2 (
    input  signed [17:0] a_q314,    // Q(3,14)
    input  signed [17:0] b_q512,    // Q(5,12)

    output signed [20:0] sum_q614,  // Q(6,14)
    output signed [20:0] sub_q614,  // Q(6,14)
    output signed [35:0] mul_q926   // Q(9,26)
);

    //ADD/SUB ALIGNMENT 

    wire signed [20:0] a_q614;
    assign a_q614 = {{3{a_q314[17]}}, a_q314};

    wire signed [20:0] b_q614;
    assign b_q614 = {{1{b_q512[17]}}, b_q512, 2'b00};

    assign sum_q614 = a_q614 + b_q614;
    assign sub_q614 = a_q614 - b_q614;

    //SHIFT-ADD MULTIPLIER

    wire signed [35:0] a_ext;
    wire signed [35:0] partial [17:0];
    wire signed [35:0] mul_temp;

    assign a_ext = {{18{a_q314[17]}}, a_q314};

    genvar i;
    generate
        for(i = 0; i < 17; i = i + 1) begin : MULT_STAGE
            assign partial[i] = b_q512[i] ? (a_ext <<< i) : 36'sd0;
        end
    endgenerate

    // sign bit handling
    assign partial[17] = b_q512[17] ? -(a_ext <<< 17) : 36'sd0;

    assign mul_temp =
          partial[0]  + partial[1]  + partial[2]  + partial[3]  +
          partial[4]  + partial[5]  + partial[6]  + partial[7]  +
          partial[8]  + partial[9]  + partial[10] + partial[11] +
          partial[12] + partial[13] + partial[14] + partial[15] +
          partial[16] + partial[17];

    assign mul_q926 = mul_temp;

endmodule

DSP LAB/Exp2_FixedPoint_Operations/tb_exp_2.v
`timescale 1ns/1ps

module tb_exp_2;

    parameter N = 48000;

    reg signed [17:0] x_q314_mem [0:N-1];
    reg signed [17:0] x_q512_mem [0:N-1];

    reg signed [17:0] a_q314;
    reg signed [17:0] b_q512;

    wire signed [20:0] sum_q614;
    wire signed [20:0] sub_q614;
    wire signed [35:0] mul_q926;

    integer f_sum, f_sub, f_mul;
    integer i, dump_count;

    integer fd1, fd2;
    integer temp1, temp2;
    integer status1, status2;

    // Instantiate DUT
    exp_2 DUT (
        .a_q314(a_q314),
        .b_q512(b_q512),
        .sum_q614(sum_q614),
        .sub_q614(sub_q614),
        .mul_q926(mul_q926)
    );

    // GTKWave dump
    initial begin
        $dumpfile("fixed_point.vcd");
        $dumpvars(0, tb_exp_2);
        dump_count = 0;
    end

    initial begin

        $display("Reading decimal input files...");

        // open decimal input files
        fd1 = $fopen("x_q314.txt", "r");
        fd2 = $fopen("x_q512.txt", "r");

        // read decimal values
        for (i = 0; i < N; i = i + 1) begin
            status1 = $fscanf(fd1, "%d\n", temp1);
            status2 = $fscanf(fd2, "%d\n", temp2);

            x_q314_mem[i] = temp1;
            x_q512_mem[i] = temp2;
        end

        $fclose(fd1);
        $fclose(fd2);

        // open output files
        f_sum = $fopen("sum_q614.txt", "w");
        f_sub = $fopen("sub_q614.txt", "w");
        f_mul = $fopen("mul_q926.txt", "w");

        // initialize inputs
        a_q314 = 0;
        b_q512 = 0;
        #10;

        // apply stimulus
        for (i = 0; i < N; i = i + 1) begin

            a_q314 = x_q314_mem[i];
            b_q512 = x_q512_mem[i];
            #10;

            // write outputs
            $fdisplay(f_sum, "%d", sum_q614);
            $fdisplay(f_sub, "%d", sub_q614);
            $fdisplay(f_mul, "%d", mul_q926);

            // limit waveform dumping
            dump_count = dump_count + 1;
            if (dump_count == 240)
                $dumpoff;
        end

        $fclose(f_sum);
        $fclose(f_sub);
        $fclose(f_mul);

        $display("Simulation complete. Output files generated.");
        $finish;
    end

endmodule

DSP LAB/Exp2_FixedPoint_Operations/fixed_point.vcd
$date
	Mon Feb 09 14:39:42 2026
$end
$version
	Icarus Verilog
$end
$timescale
	1ps
$end
$scope module tb_exp_2 $end
$var wire 21 ! sum_q614 [20:0] $end
$var wire 21 " sub_q614 [20:0] $end
$var wire 36 # mul_q926 [35:0] $end
$var parameter 32 $ N $end
$var reg 18 % a_q314 [17:0] $end
$var reg 18 & b_q512 [17:0] $end
$var integer 32 ' dump_count [31:0] $end
$var integer 32 ( f_mul [31:0] $end
$var integer 32 ) f_sub [31:0] $end
$var integer 32 * f_sum [31:0] $end
$var integer 32 + fd1 [31:0] $end
$var integer 32 , fd2 [31:0] $end
$var integer 32 - i [31:0] $end
$var integer 32 . status1 [31:0] $end
$var integer 32 / status2 [31:0] $end
$var integer 32 0 temp1 [31:0] $end
$var integer 32 1 temp2 [31:0] $end
$scope module DUT $end
$var wire 18 2 a_q314 [17:0] $end
$var wire 18 3 b_q512 [17:0] $end
$var wire 36 4 mul_q926 [35:0] $end
$var wire 21 5 sum_q614 [20:0] $end
$var wire 21 6 sub_q614 [20:0] $end
$var wire 36 7 mul_temp [35:0] $end
$var wire 21 8 b_q614 [20:0] $end
$var wire 21 9 a_q614 [20:0] $end
$var wire 36 : a_ext [35:0] $end
$scope begin MULT_STAGE[0] $end
$var parameter 2 ; i $end
$upscope $end
$scope begin MULT_STAGE[1] $end
$var parameter 2 < i $end
$upscope $end
$scope begin MULT_STAGE[2] $end
$var parameter 3 = i $end
$upscope $end
$scope begin MULT_STAGE[3] $end
$var parameter 3 > i $end
$upscope $end
$scope begin MULT_STAGE[4] $end
$var parameter 4 ? i $end
$upscope $end
$scope begin MULT_STAGE[5] $end
$var parameter 4 @ i $end
$upscope $end
$scope begin MULT_STAGE[6] $end
$var parameter 4 A i $end
$upscope $end
$scope begin MULT_STAGE[7] $end
$var parameter 4 B i $end
$upscope $end
$scope begin MULT_STAGE[8] $end
$var parameter 5 C i $end
$upscope $end
$scope begin MULT_STAGE[9] $end
$var parameter 5 D i $end
$upscope $end
$scope begin MULT_STAGE[10] $end
$var parameter 5 E i $end
$upscope $end
$scope begin MULT_STAGE[11] $end
$var parameter 5 F i $end
$upscope $end
$scope begin MULT_STAGE[12] $end
$var parameter 5 G i $end
$upscope $end
$scope begin MULT_STAGE[13] $end
$var parameter 5 H i $end
$upscope $end
$scope begin MULT_STAGE[14] $end
$var parameter 5 I i $end
$upscope $end
$scope begin MULT_STAGE[15] $end
$var parameter 5 J i $end
$upscope $end
$scope begin MULT_STAGE[16] $end
$var parameter 6 K i $end
$upscope $end
$upscope $end
$upscope $end
$enddefinitions $end
$comment Show the parameter values. $end
$dumpall
b10000 K
b1111 J
b1110 I
b1101 H
b1100 G
b1011 F
b1010 E
b1001 D
b1000 C
b111 B
b110 A
b101 @
b100 ?
b11 >
b10 =
b1 <
b0 ;
b1011101110000000 $
$end
#0
$dumpvars
b0 :
b0 9
b0 8
b0 7
b0 6
b0 5
b0 4
b0 3
b0 2
b11111111111111111111101111010011 1
b11111111111111111110111101001011 0
b1 /
b1 .
b1011101110000000 -
b10000000000000000000000000000100 ,
b10000000000000000000000000000011 +
b10000000000000000000000000000011 *
b10000000000000000000000000000100 )
b10000000000000000000000000000101 (
b0 '
b0 &
b0 %
b0 #
b0 "
b0 !
$end
#10000
b0 -
#20000
b10001011100001111010001 #
b10001011100001111010001 4
b10001011100001111010001 7
b1000010110100 8
b10000101101 &
b10000101101 3
b10000101101001 !
b10000101101001 5
b1 "
b1 6
b1000010110101 9
b1000010110101 :
b1000010110101 %
b1000010110101 2
b1 -
b1 '
#30000
b1000100100101100101001000 #
b1000100100101100101001000 4
b1000100100101100101001000 7
b10000100100000 8
b100001001000 &
b100001001000 3
b100001001000001 !
b100001001000001 5
b1 "
b1 6
b10000100100001 9
b10000100100001 :
b10000100100001 %
b10000100100001 2
b10 -
b10 '
#40000
b10010101111101111000000100 #
b10010101111101111000000100 4
b10010101111101111000000100 7
b11000011111100 8
b110000111111 &
b110000111111 3
b110000111111000 !
b110000111111000 5
b0 "
b0 6
b11000011111100 9
b11000011111100 :
b11000011111100 %
b11000011111100 2
b11 -
b11 '
#50000
b100000000000000000000000000 #
b100000000000000000000000000 4
b100000000000000000000000000 7
b100000000000000 8
b1000000000000 &
b1000000000000 3
b1000000000000000 !
b1000000000000000 5
b0 "
b0 6
b100000000000000 9
b100000000000000 :
b100000000000000 %
b100000000000000 2
b100 -
b100 '
#60000
b101111011011111010001100100 #
b101111011011111010001100100 4
b101111011011111010001100100 7
b100110111101100 8
b1001101111011 &
b1001101111011 3
b1001101111011000 !
b1001101111011000 5
b0 "
b0 6
b100110111101100 9
b100110111101100 :
b100110111101100 %
b100110111101100 2
b101 -
b101 '
#70000
b1000000000000001011111000010 #
b1000000000000001011111000010 4
b1000000000000001011111000010 7
b101101010000100 8
b1011010100001 &
b1011010100001 3
b1011010100000110 !
b1011010100000110 5
b111111111111111111110 "
b111111111111111111110 6
b101101010000010 9
b101101010000010 :
b101101010000010 %
b101101010000010 2
b110 -
b110 '
#80000
b1010000100100000101010000111 #
b1010000100100000101010000111 4
b1010000100100000101010000111 7
b110010110001100 8
b1100101100011 &
b1100101100011 3
b1100101100011001 !
b1100101100011001 5
b1 "
b1 6
b110010110001101 9
b110010110001101 :
b110010110001101 %
b110010110001101 2
b111 -
b111 '
#90000
b1011111111111100110011111100 #
b1011111111111100110011111100 4
b1011111111111100110011111100 7
b110111011011000 8
b1101110110110 &
b1101110110110 3
b1101110110110010 !
b1101110110110010 5
b10 "
b10 6
b110111011011010 9
b110111011011010 :
b110111011011010 %
b110111011011010 2
b1000 -
b1000 '
#100000
b1101101001111111111100100000 #
b1101101001111111111100100000 4
b1101101001111111111100100000 7
b111011001000000 8
b1110110010000 &
b1110110010000 3
b1110110010000010 !
b1110110010000010 5
b10 "
b10 6
b111011001000010 9
b111011001000010 :
b111011001000010 %
b111011001000010 2
b1001 -
b1001 '
#110000
b1110111011011010000101011011 #
b1110111011011010000101011011 4
b1110111011011010000101011011 7
b111101110100100 8
b1111011101001 &
b1111011101001 3
b1111011101000111 !
b1111011101000111 5
b111111111111111111111 "
b111111111111111111111 6
b111101110100011 9
b111101110100011 :
b111101110100011 %
b111101110100011 2
b1010 -
b1010 '
#120000
b1111101110100100110010010000 #
b1111101110100100110010010000 4
b1111101110100100110010010000 7
b111111011101000 8
b1111110111010 &
b1111110111010 3
b1111110111010000 !
b1111110111010000 5
b0 "
b0 6
b111111011101000 9
b111111011101000 :
b111111011101000 %
b111111011101000 2
b1011 -
b1011 '
#130000
b10000000000000000000000000000 #
b10000000000000000000000000000 4
b10000000000000000000000000000 7
b1000000000000000 8
b10000000000000 &
b10000000000000 3
b10000000000000000 !
b10000000000000000 5
b0 "
b0 6
b1000000000000000 9
b1000000000000000 :
b1000000000000000 %
b1000000000000000 2
b1100 -
b1100 '
#140000
b1111101110100100110010010000 #
b1111101110100100110010010000 4
b1111101110100100110010010000 7
b111111011101000 8
b1111110111010 &
b1111110111010 3
b1111110111010000 !
b1111110111010000 5
b0 "
b0 6
b111111011101000 9
b111111011101000 :
b111111011101000 %
b111111011101000 2
b1101 -
b1101 '
#150000
b1110111011011010000101011011 #
b1110111011011010000101011011 4
b1110111011011010000101011011 7
b111101110100100 8
b1111011101001 &
b1111011101001 3
b1111011101000111 !
b1111011101000111 5
b111111111111111111111 "
b111111111111111111111 6
b111101110100011 9
b111101110100011 :
b111101110100011 %
b111101110100011 2
b1110 -
b1110 '
#160000
b1101101001111111111100100000 #
b1101101001111111111100100000 4
b1101101001111111111100100000 7
b111011001000000 8
b1110110010000 &
b1110110010000 3
b1110110010000010 !
b1110110010000010 5
b10 "
b10 6
b111011001000010 9
b111011001000010 :
b111011001000010 %
b111011001000010 2
b1111 -
b1111 '
#170000
b1011111111111100110011111100 #
b1011111111111100110011111100 4
b1011111111111100110011111100 7
b110111011011000 8
b1101110110110 &
b1101110110110 3
b1101110110110010 !
b1101110110110010 5
b10 "
b10 6
b110111011011010 9
b110111011011010 :
b110111011011010 %
b110111011011010 2
b10000 -
b10000 '
#180000
b1010000100100000101010000111 #
b1010000100100000101010000111 4
b1010000100100000101010000111 7
b110010110001100 8
b1100101100011 &
b1100101100011 3
b1100101100011001 !
b1100101100011001 5
b1 "
b1 6
b110010110001101 9
b110010110001101 :
b110010110001101 %
b110010110001101 2
b10001 -
b10001 '
#190000
b1000000000000001011111000010 #
b1000000000000001011111000010 4
b1000000000000001011111000010 7
b101101010000100 8
b1011010100001 &
b1011010100001 3
b1011010100000110 !
b1011010100000110 5
b111111111111111111110 "
b111111111111111111110 6
b101101010000010 9
b101101010000010 :
b101101010000010 %
b101101010000010 2
b10010 -
b10010 '
#200000
b101111011011111010001100100 #
b101111011011111010001100100 4
b101111011011111010001100100 7
b100110111101100 8
b1001101111011 &
b1001101111011 3
b1001101111011000 !
b1001101111011000 5
b0 "
b0 6
b100110111101100 9
b100110111101100 :
b100110111101100 %
b100110111101100 2
b10011 -
b10011 '
#210000
b100000000000000000000000000 #
b100000000000000000000000000 4
b100000000000000000000000000 7
b100000000000000 8
b1000000000000 &
b1000000000000 3
b1000000000000000 !
b1000000000000000 5
b0 "
b0 6
b100000000000000 9
b100000000000000 :
b100000000000000 %
b100000000000000 2
b10100 -
b10100 '
#220000
b10010101111101111000000100 #
b10010101111101111000000100 4
b10010101111101111000000100 7
b11000011111100 8
b110000111111 &
b110000111111 3
b110000111111000 !
b110000111111000 5
b0 "
b0 6
b11000011111100 9
b11000011111100 :
b11000011111100 %
b11000011111100 2
b10101 -
b10101 '
#230000
b1000100100101100101001000 #
b1000100100101100101001000 4
b1000100100101100101001000 7
b10000100100000 8
b100001001000 &
b100001001000 3
b100001001000001 !
b100001001000001 5
b1 "
b1 6
b10000100100001 9
b10000100100001 :
b10000100100001 %
b10000100100001 2
b10110 -
b10110 '
#240000
b10001011100001111010001 #
b10001011100001111010001 4
b10001011100001111010001 7
b1000010110100 8
b10000101101 &
b10000101101 3
b10000101101001 !
b10000101101001 5
b1 "
b1 6
b1000010110101 9
b1000010110101 :
b1000010110101 %
b1000010110101 2
b10111 -
b10111 '
#250000
b0 #
b0 4
b0 7
b0 8
b0 &
b0 3
b0 !
b0 5
b0 "
b0 6
b0 9
b0 :
b0 %
b0 2
b11000 -
b11000 '
#260000
b10001011100001111010001 #
b10001011100001111010001 4
b10001011100001111010001 7
b111111110111101001100 8
b111111101111010011 &
b111111101111010011 3
b111111101111010010111 !
b111111101111010010111 5
b111111111111111111111 "
b111111111111111111111 6
b111111110111101001011 9
b111111111111111111111110111101001011 :
b111110111101001011 %
b111110111101001011 2
b11001 -
b11001 '
#270000
b1000100100101100101001000 #
b1000100100101100101001000 4
b1000100100101100101001000 7
b111111101111011100000 8
b111111011110111000 &
b111111011110111000 3
b111111011110110111111 !
b111111011110110111111 5
b111111111111111111111 "
b111111111111111111111 6
b111111101111011011111 9
b111111111111111111111101111011011111 :
b111101111011011111 %
b111101111011011111 2
b11010 -
b11010 '
#280000
b10010101111101111000000100 #
b10010101111101111000000100 4
b10010101111101111000000100 7
b111111100111100000100 8
b111111001111000001 &
b111111001111000001 3
b111111001111000001000 !
b111111001111000001000 5
b0 "
b0 6
b111111100111100000100 9
b111111111111111111111100111100000100 :
b111100111100000100 %
b111100111100000100 2
b11011 -
b11011 '
#290000
b100000000000000000000000000 #
b100000000000000000000000000 4
b100000000000000000000000000 7
b111111100000000000000 8
b111111000000000000 &
b111111000000000000 3
b111111000000000000000 !
b111111000000000000000 5
b0 "
b0 6
b111111100000000000000 9
b111111111111111111111100000000000000 :
b111100000000000000 %
b111100000000000000 2
b11100 -
b11100 '
#300000
b101111011011111010001100100 #
b101111011011111010001100100 4
b101111011011111010001100100 7
b111111011001000010100 8
b111110110010000101 &
b111110110010000101 3
b111110110010000101000 !
b111110110010000101000 5
b0 "
b0 6
b111111011001000010100 9
b111111111111111111111011001000010100 :
b111011001000010100 %
b111011001000010100 2
b11101 -
b11101 '
#310000
b1000000000000001011111000010 #
b1000000000000001011111000010 4
b1000000000000001011111000010 7
b111111010010101111100 8
b111110100101011111 &
b111110100101011111 3
b111110100101011111010 !
b111110100101011111010 5
b10 "
b10 6
b111111010010101111110 9
b111111111111111111111010010101111110 :
b111010010101111110 %
b111010010101111110 2
b11110 -
b11110 '
#320000
b1010000100100000101010000111 #
b1010000100100000101010000111 4
b1010000100100000101010000111 7
b111111001101001110100 8
b111110011010011101 &
b111110011010011101 3
b111110011010011100111 !
b111110011010011100111 5
b111111111111111111111 "
b111111111111111111111 6
b111111001101001110011 9
b111111111111111111111001101001110011 :
b111001101001110011 %
b111001101001110011 2
b11111 -
b11111 '
#330000
b1011111111111100110011111100 #
b1011111111111100110011111100 4
b1011111111111100110011111100 7
b111111001000100101000 8
b111110010001001010 &
b111110010001001010 3
b111110010001001001110 !
b111110010001001001110 5
b111111111111111111110 "
b111111111111111111110 6
b111111001000100100110 9
b111111111111111111111001000100100110 :
b111001000100100110 %
b111001000100100110 2
b100000 -
b100000 '
#340000
b1101101001111111111100100000 #
b1101101001111111111100100000 4
b1101101001111111111100100000 7
b111111000100111000000 8
b111110001001110000 &
b111110001001110000 3
b111110001001101111110 !
b111110001001101111110 5
b111111111111111111110 "
b111111111111111111110 6
b111111000100110111110 9
b111111111111111111111000100110111110 :
b111000100110111110 %
b111000100110111110 2
b100001 -
b100001 '
#350000
b1110111011011010000101011011 #
b1110111011011010000101011011 4
b1110111011011010000101011011 7
b111111000010001011100 8
b111110000100010111 &
b111110000100010111 3
b111110000100010111001 !
b111110000100010111001 5
b1 "
b1 6
b111111000010001011101 9
b111111111111111111111000010001011101 :
b111000010001011101 %
b111000010001011101 2
b100010 -
b100010 '
#360000
b1111101110100100110010010000 #
b1111101110100100110010010000 4
b1111101110100100110010010000 7
b111111000000100011000 8
b111110000001000110 &
b111110000001000110 3
b111110000001000110000 !
b111110000001000110000 5
b0 "
b0 6
b111111000000100011000 9
b111111111111111111111000000100011000 :
b111000000100011000 %
b111000000100011000 2
b100011 -
b100011 '
#370000
b10000000000000000000000000000 #
b10000000000000000000000000000 4
b10000000000000000000000000000 7
b111111000000000000000 8
b111110000000000000 &
b111110000000000000 3
b111110000000000000000 !
b111110000000000000000 5
b0 "
b0 6
b111111000000000000000 9
b111111111111111111111000000000000000 :
b111000000000000000 %
b111000000000000000 2
b100100 -
b100100 '
#380000
b1111101110100100110010010000 #
b1111101110100100110010010000 4
b1111101110100100110010010000 7
b111111000000100011000 8
b111110000001000110 &
b111110000001000110 3
b111110000001000110000 !
b111110000001000110000 5
b0 "
b0 6
b111111000000100011000 9
b111111111111111111111000000100011000 :
b111000000100011000 %
b111000000100011000 2
b100101 -
b100101 '
#390000
b1110111011011010000101011011 #
b1110111011011010000101011011 4
b1110111011011010000101011011 7
b111111000010001011100 8
b111110000100010111 &
b111110000100010111 3
b111110000100010111001 !
b111110000100010111001 5
b1 "
b1 6
b111111000010001011101 9
b111111111111111111111000010001011101 :
b111000010001011101 %
b111000010001011101 2
b100110 -
b100110 '
#400000
b1101101001111111111100100000 #
b1101101001111111111100100000 4
b1101101001111111111100100000 7
b111111000100111000000 8
b111110001001110000 &
b111110001001110000 3
b111110001001101111110 !
b111110001001101111110 5
b111111111111111111110 "
b111111111111111111110 6
b111111000100110111110 9
b111111111111111111111000100110111110 :
b111000100110111110 %
b111000100110111110 2
b100111 -
b100111 '
#410000
b1011111111111100110011111100 #
b1011111111111100110011111100 4
b1011111111111100110011111100 7
b111111001000100101000 8
b111110010001001010 &
b111110010001001010 3
b111110010001001001110 !
b111110010001001001110 5
b111111111111111111110 "
b111111111111111111110 6
b111111001000100100110 9
b111111111111111111111001000100100110 :
b111001000100100110 %
b111001000100100110 2
b101000 -
b101000 '
#420000
b1010000100100000101010000111 #
b1010000100100000101010000111 4
b1010000100100000101010000111 7
b111111001101001110100 8
b111110011010011101 &
b111110011010011101 3
b111110011010011100111 !
b111110011010011100111 5
b111111111111111111111 "
b111111111111111111111 6
b111111001101001110011 9
b111111111111111111111001101001110011 :
b111001101001110011 %
b111001101001110011 2
b101001 -
b101001 '
#430000
b1000000000000001011111000010 #
b1000000000000001011111000010 4
b1000000000000001011111000010 7
b111111010010101111100 8
b111110100101011111 &
b111110100101011111 3
b111110100101011111010 !
b111110100101011111010 5
b10 "
b10 6
b111111010010101111110 9
b111111111111111111111010010101111110 :
b111010010101111110 %
b111010010101111110 2
b101010 -
b101010 '
#440000
b101111011011111010001100100 #
b101111011011111010001100100 4
b101111011011111010001100100 7
b111111011001000010100 8
b111110110010000101 &
b111110110010000101 3
b111110110010000101000 !
b111110110010000101000 5
b0 "
b0 6
b111111011001000010100 9
b111111111111111111111011001000010100 :
b111011001000010100 %
b111011001000010100 2
b101011 -
b101011 '
#450000
b100000000000000000000000000 #
b100000000000000000000000000 4
b100000000000000000000000000 7
b111111100000000000000 8
b111111000000000000 &
b111111000000000000 3
b111111000000000000000 !
b111111000000000000000 5
b0 "
b0 6
b111111100000000000000 9
b111111111111111111111100000000000000 :
b111100000000000000 %
b111100000000000000 2
b101100 -
b101100 '
#460000
b10010101111101111000000100 #
b10010101111101111000000100 4
b10010101111101111000000100 7
b111111100111100000100 8
b111111001111000001 &
b111111001111000001 3
b111111001111000001000 !
b111111001111000001000 5
b0 "
b0 6
b111111100111100000100 9
b111111111111111111111100111100000100 :
b111100111100000100 %
b111100111100000100 2
b101101 -
b101101 '
#470000
b1000100100101100101001000 #
b1000100100101100101001000 4
b1000100100101100101001000 7
b111111101111011100000 8
b111111011110111000 &
b111111011110111000 3
b111111011110110111111 !
b111111011110110111111 5
b111111111111111111111 "
b111111111111111111111 6
b111111101111011011111 9
b111111111111111111111101111011011111 :
b111101111011011111 %
b111101111011011111 2
b101110 -
b101110 '
#480000
b10001011100001111010001 #
b10001011100001111010001 4
b10001011100001111010001 7
b111111110111101001100 8
b111111101111010011 &
b111111101111010011 3
b111111101111010010111 !
b111111101111010010111 5
b111111111111111111111 "
b111111111111111111111 6
b111111110111101001011 9
b111111111111111111111110111101001011 :
b111110111101001011 %
b111110111101001011 2
b101111 -
b101111 '
#490000
b0 #
b0 4
b0 7
b0 8
b0 &
b0 3
b0 !
b0 5
b0 "
b0 6
b0 9
b0 :
b0 %
b0 2
b110000 -
b110000 '
#500000
b10001011100001111010001 #
b10001011100001111010001 4
b10001011100001111010001 7
b1000010110100 8
b10000101101 &
b10000101101 3
b10000101101001 !
b10000101101001 5
b1 "
b1 6
b1000010110101 9
b1000010110101 :
b1000010110101 %
b1000010110101 2
b110001 -
b110001 '
#510000
b1000100100101100101001000 #
b1000100100101100101001000 4
b1000100100101100101001000 7
b10000100100000 8
b100001001000 &
b100001001000 3
b100001001000001 !
b100001001000001 5
b1 "
b1 6
b10000100100001 9
b10000100100001 :
b10000100100001 %
b10000100100001 2
b110010 -
b110010 '
#520000
b10010101111101111000000100 #
b10010101111101111000000100 4
b10010101111101111000000100 7
b11000011111100 8
b110000111111 &
b110000111111 3
b110000111111000 !
b110000111111000 5
b0 "
b0 6
b11000011111100 9
b11000011111100 :
b11000011111100 %
b11000011111100 2
b110011 -
b110011 '
#530000
b100000000000000000000000000 #
b100000000000000000000000000 4
b100000000000000000000000000 7
b100000000000000 8
b1000000000000 &
b1000000000000 3
b1000000000000000 !
b1000000000000000 5
b0 "
b0 6
b100000000000000 9
b100000000000000 :
b100000000000000 %
b100000000000000 2
b110100 -
b110100 '
#540000
b101111011011111010001100100 #
b101111011011111010001100100 4
b101111011011111010001100100 7
b100110111101100 8
b1001101111011 &
b1001101111011 3
b1001101111011000 !
b1001101111011000 5
b0 "
b0 6
b100110111101100 9
b100110111101100 :
b100110111101100 %
b100110111101100 2
b110101 -
b110101 '
#550000
b1000000000000001011111000010 #
b1000000000000001011111000010 4
b1000000000000001011111000010 7
b101101010000100 8
b1011010100001 &
b1011010100001 3
b1011010100000110 !
b1011010100000110 5
b111111111111111111110 "
b111111111111111111110 6
b101101010000010 9
b101101010000010 :
b101101010000010 %
b101101010000010 2
b110110 -
b110110 '
#560000
b1010000100100000101010000111 #
b1010000100100000101010000111 4
b1010000100100000101010000111 7
b110010110001100 8
b1100101100011 &
b1100101100011 3
b1100101100011001 !
b1100101100011001 5
b1 "
b1 6
b110010110001101 9
b110010110001101 :
b110010110001101 %
b110010110001101 2
b110111 -
b110111 '
#570000
b1011111111111100110011111100 #
b1011111111111100110011111100 4
b1011111111111100110011111100 7
b110111011011000 8
b1101110110110 &
b1101110110110 3
b1101110110110010 !
b1101110110110010 5
b10 "
b10 6
b110111011011010 9
b110111011011010 :
b110111011011010 %
b110111011011010 2
b111000 -
b111000 '
#580000
b1101101001111111111100100000 #
b1101101001111111111100100000 4
b1101101001111111111100100000 7
b111011001000000 8
b1110110010000 &
b1110110010000 3
b1110110010000010 !
b1110110010000010 5
b10 "
b10 6
b111011001000010 9
b111011001000010 :
b111011001000010 %
b111011001000010 2
b111001 -
b111001 '
#590000
b1110111011011010000101011011 #
b1110111011011010000101011011 4
b1110111011011010000101011011 7
b111101110100100 8
b1111011101001 &
b1111011101001 3
b1111011101000111 !
b1111011101000111 5
b111111111111111111111 "
b111111111111111111111 6
b111101110100011 9
b111101110100011 :
b111101110100011 %
b111101110100011 2
b111010 -
b111010 '
#600000
b1111101110100100110010010000 #
b1111101110100100110010010000 4
b1111101110100100110010010000 7
b111111011101000 8
b1111110111010 &
b1111110111010 3
b1111110111010000 !
b1111110111010000 5
b0 "
b0 6
b111111011101000 9
b111111011101000 :
b111111011101000 %
b111111011101000 2
b111011 -
b111011 '
#610000
b10000000000000000000000000000 #
b10000000000000000000000000000 4
b10000000000000000000000000000 7
b1000000000000000 8
b10000000000000 &
b10000000000000 3
b10000000000000000 !
b10000000000000000 5
b0 "
b0 6
b1000000000000000 9
b1000000000000000 :
b1000000000000000 %
b1000000000000000 2
b111100 -
b111100 '
#620000
b1111101110100100110010010000 #
b1111101110100100110010010000 4
b1111101110100100110010010000 7
b111111011101000 8
b1111110111010 &
b1111110111010 3
b1111110111010000 !
b1111110111010000 5
b0 "
b0 6
b111111011101000 9
b111111011101000 :
b111111011101000 %
b111111011101000 2
b111101 -
b111101 '
#630000
b1110111011011010000101011011 #
b1110111011011010000101011011 4
b1110111011011010000101011011 7
b111101110100100 8
b1111011101001 &
b1111011101001 3
b1111011101000111 !
b1111011101000111 5
b111111111111111111111 "
b111111111111111111111 6
b111101110100011 9
b111101110100011 :
b111101110100011 %
b111101110100011 2
b111110 -
b111110 '
#640000
b1101101001111111111100100000 #
b1101101001111111111100100000 4
b1101101001111111111100100000 7
b111011001000000 8
b1110110010000 &
b1110110010000 3
b1110110010000010 !
b1110110010000010 5
b10 "
b10 6
b111011001000010 9
b111011001000010 :
b111011001000010 %
b111011001000010 2
b111111 -
b111111 '
#650000
b1011111111111100110011111100 #
b1011111111111100110011111100 4
b1011111111111100110011111100 7
b110111011011000 8
b1101110110110 &
b1101110110110 3
b1101110110110010 !
b1101110110110010 5
b10 "
b10 6
b110111011011010 9
b110111011011010 :
b110111011011010 %
b110111011011010 2
b1000000 -
b1000000 '
#660000
b1010000100100000101010000111 #
b1010000100100000101010000111 4
b1010000100100000101010000111 7
b110010110001100 8
b1100101100011 &
b1100101100011 3
b1100101100011001 !
b1100101100011001 5
b1 "
b1 6
b110010110001101 9
b110010110001101 :
b110010110001101 %
b110010110001101 2
b1000001 -
b1000001 '
#670000
b1000000000000001011111000010 #
b1000000000000001011111000010 4
b1000000000000001011111000010 7
b101101010000100 8
b1011010100001 &
b1011010100001 3
b1011010100000110 !
b1011010100000110 5
b111111111111111111110 "
b111111111111111111110 6
b101101010000010 9
b101101010000010 :
b101101010000010 %
b101101010000010 2
b1000010 -
b1000010 '
#680000
b101111011011111010001100100 #
b101111011011111010001100100 4
b101111011011111010001100100 7
b100110111101100 8
b1001101111011 &
b1001101111011 3
b1001101111011000 !
b1001101111011000 5
b0 "
b0 6
b100110111101100 9
b100110111101100 :
b100110111101100 %
b100110111101100 2
b1000011 -
b1000011 '
#690000
b100000000000000000000000000 #
b100000000000000000000000000 4
b100000000000000000000000000 7
b100000000000000 8
b1000000000000 &
b1000000000000 3
b1000000000000000 !
b1000000000000000 5
b0 "
b0 6
b100000000000000 9
b100000000000000 :
b100000000000000 %
b100000000000000 2
b1000100 -
b1000100 '
#700000
b10010101111101111000000100 #
b10010101111101111000000100 4
b10010101111101111000000100 7
b11000011111100 8
b110000111111 &
b110000111111 3
b110000111111000 !
b110000111111000 5
b0 "
b0 6
b11000011111100 9
b11000011111100 :
b11000011111100 %
b11000011111100 2
b1000101 -
b1000101 '
#710000
b1000100100101100101001000 #
b1000100100101100101001000 4
b1000100100101100101001000 7
b10000100100000 8
b100001001000 &
b100001001000 3
b100001001000001 !
b100001001000001 5
b1 "
b1 6
b10000100100001 9
b10000100100001 :
b10000100100001 %
b10000100100001 2
b1000110 -
b1000110 '
#720000
b10001011100001111010001 #
b10001011100001111010001 4
b10001011100001111010001 7
b1000010110100 8
b10000101101 &
b10000101101 3
b10000101101001 !
b10000101101001 5
b1 "
b1 6
b1000010110101 9
b1000010110101 :
b1000010110101 %
b1000010110101 2
b1000111 -
b1000111 '
#730000
b0 #
b0 4
b0 7
b0 8
b0 &
b0 3
b0 !
b0 5
b0 "
b0 6
b0 9
b0 :
b0 %
b0 2
b1001000 -
b1001000 '
#740000
b10001011100001111010001 #
b10001011100001111010001 4
b10001011100001111010001 7
b111111110111101001100 8
b111111101111010011 &
b111111101111010011 3
b111111101111010010111 !
b111111101111010010111 5
b111111111111111111111 "
b111111111111111111111 6
b111111110111101001011 9
b111111111111111111111110111101001011 :
b111110111101001011 %
b111110111101001011 2
b1001001 -
b1001001 '
#750000
b1000100100101100101001000 #
b1000100100101100101001000 4
b1000100100101100101001000 7
b111111101111011100000 8
b111111011110111000 &
b111111011110111000 3
b111111011110110111111 !
b111111011110110111111 5
b111111111111111111111 "
b111111111111111111111 6
b111111101111011011111 9
b111111111111111111111101111011011111 :
b111101111011011111 %
b111101111011011111 2
b1001010 -
b1001010 '
